xml_iterator-0.1.4.dist-info/METADATA
xml_iterator-0.1.4.dist-info/WHEEL
xml_iterator/__init__.py
xml_iterator/core.py
xml_iterator/xml_iterator.cp312-win_amd64.pyd
xml_iterator-0.1.4.dist-info/RECORD
